{
  "queries": [
    {
      "id": "implementation-onboarding-table",
      "name": "Implementation Onboarding Table",
      "description": "Deals in Project Handover for companies in Customer Onboarding, one row per deal x product family (HR & Payroll / PeopleBox) with per-family MRR, implementation fee, fee status, bundle contents, and the company's implementation fields (PM, KOM dates, HR URL, etc.). For the Implementation team's app.",
      "tags": [
        "Implementation",
        "Onboarding",
        "Company",
        "Deal",
        "Line Items"
      ],
      "sql": "WITH li_fam AS (\n  SELECT\n    CAST(li.deal_id AS BIGINT) AS deal_key,\n    CASE WHEN lower(li.product_name) LIKE '%peoplebox%' OR lower(li.parent_product) LIKE '%peoplebox%'\n         THEN 'PeopleBox' ELSE 'HR & Payroll' END AS product_family,\n    CASE WHEN li.recurring_billing_frequency IS NOT NULL\n          AND lower(trim(li.recurring_billing_frequency)) <> 'one time payment'\n          AND li.contract_term_months >= 12\n          AND NOT (li.product_name = 'Instacash' OR li.product_name LIKE '%Ready%')\n         THEN li.mrr ELSE 0 END AS li_mrr,\n    CASE WHEN lower(li.product_name) LIKE '%implement%' THEN li.amount ELSE 0 END AS li_implem,\n    CASE WHEN li.bundled_products IS NOT NULL AND li.bundled_products NOT IN ('None','')\n         THEN li.bundled_products END AS bundled_clean\n  FROM shared.revops.silver_line_items li\n  WHERE li.tribe_new = 'Core'\n     OR lower(li.product_name)   LIKE '%peoplebox%'\n     OR lower(li.parent_product) LIKE '%peoplebox%'\n     OR lower(li.product_name)   LIKE '%implement%'\n),\nfam AS (\n  SELECT deal_key, product_family,\n         SUM(li_mrr)                                  AS fam_mrr,\n         SUM(li_implem)                               AS fam_implem,\n         array_join(collect_set(bundled_clean), ' | ') AS bundled_products\n  FROM li_fam GROUP BY deal_key, product_family\n)\nSELECT\n  d.deal_id, d.deal_name, d.stage_label AS deal_stage,\n  c.Company_name AS company_name, c.Client_stage AS client_stage, c.Client_status AS client_status,\n  fam.product_family, fam.bundled_products, fam.fam_mrr AS mrr, fam.fam_implem AS implem_fee_amount,\n  CASE WHEN NULLIF(TRIM(c.Implementation_fee_status),'') IS NOT NULL THEN c.Implementation_fee_status\n       WHEN fam.fam_implem = 0 THEN 'Waived'\n       WHEN fam.fam_implem > 0 THEN 'Paid' ELSE NULL END AS implem_fee_waive_or_paid,\n  c.Segment AS segment, c.Implem_packages AS implem_packages, c.Project_manager AS project_manager,\n  c.Payroll_master AS payroll_master, c.Sales_Consultant AS salesperson, c.Headcount AS headcount,\n  c.Proposal_date AS proposal_date, c.NPN_date AS npn_date, c.NPN_month AS npn_month,\n  c.Welcome_email_date AS welcome_email_date, c.Target_KOM AS target_kom, c.Actual_KOM AS actual_kom,\n  c.KOM_month AS kom_month, c.KOM_quarter AS kom_quarter, c.KOM_year AS kom_year,\n  c.Project_handover_date AS project_handover, c.Sprout_hr_url AS sprout_hr_url,\n  c.Payroll_company_code AS sprout_payroll_code, c.Churn_effectivity_date AS churn_date,\n  c.Industry AS industry, c.Company_address AS company_address\nFROM fam\nJOIN shared.revops.silver_deals   d ON CAST(d.deal_id AS BIGINT) = fam.deal_key\nLEFT JOIN shared.revops.silver_company c ON CAST(d.company_id AS BIGINT) = CAST(c.Company_id AS BIGINT)\nWHERE d.stage_label = 'Project Handover' AND c.Client_stage = 'Customer Onboarding'\nORDER BY c.Company_name, d.deal_id, product_family",
      "ownerEmail": "lurbina@sprout.ph",
      "ownerName": "lurbina",
      "createdAt": "2026-07-13T00:00:00.000Z",
      "updatedAt": "2026-07-13T00:00:00.000Z"
    }
  ]
}