{
  "dashboards": [
    {
      "id": "mcp-test-dashboard-mqyrtk51",
      "name": "MCP Test Dashboard",
      "desc": "temporary test",
      "tags": [],
      "ownerEmail": "lurbina@sprout.ph",
      "ownerName": "lurbina",
      "file": "user-dashboards/mcp-test-dashboard-mqyrtk51.html",
      "url": "https://radar-revops.vercel.app/user-dashboards/mcp-test-dashboard-mqyrtk51.html",
      "status": "private",
      "createdAt": "2026-06-29T05:22:10.734Z",
      "updatedAt": "2026-06-29T05:22:10.734Z",
      "requestedAt": null,
      "publishedAt": null
    }
  ]
}